{"errors":[],"warnings":[],"namedChunkGroups":{"app":{"chunks":[5,0,1],"assets":["webpack-runtime-2b961907fbb56a541807.js","webpack-runtime-2b961907fbb56a541807.js.map","commons-d77018590a8d9c757f2f.js","commons-d77018590a8d9c757f2f.js.map","app-92d2bdf5636a3bb2c730.js","app-92d2bdf5636a3bb2c730.js.map"],"children":{},"childAssets":{}},"component---src-pages-404-js":{"chunks":[0,2],"assets":["commons-d77018590a8d9c757f2f.js","commons-d77018590a8d9c757f2f.js.map","component---src-pages-404-js-11dabcf4a4271b9b2f12.js","component---src-pages-404-js-11dabcf4a4271b9b2f12.js.map"],"children":{},"childAssets":{}},"component---src-pages-index-js":{"chunks":[4,0,3],"assets":["styles.4c495c889fa1ef2c2b97.css","styles-32c57dba0ec3208af39e.js","styles-32c57dba0ec3208af39e.js.map","commons-d77018590a8d9c757f2f.js","commons-d77018590a8d9c757f2f.js.map","component---src-pages-index-js-d273a4ab4652745b97fd.js","component---src-pages-index-js-d273a4ab4652745b97fd.js.map"],"children":{},"childAssets":{}}},"assetsByChunkName":{"app":["webpack-runtime-2b961907fbb56a541807.js","commons-d77018590a8d9c757f2f.js","app-92d2bdf5636a3bb2c730.js"],"component---src-pages-404-js":["commons-d77018590a8d9c757f2f.js","component---src-pages-404-js-11dabcf4a4271b9b2f12.js"],"component---src-pages-index-js":["styles.4c495c889fa1ef2c2b97.css","styles-32c57dba0ec3208af39e.js","commons-d77018590a8d9c757f2f.js","component---src-pages-index-js-d273a4ab4652745b97fd.js"]}}